Telexy/Constants.py
Telexy/__init__.py
Telexy/DS/Fuse.py
Telexy/DS/FusionFS.py
Telexy/DS/VirtualFileAccessor.py
Telexy/DS/__init__.py
Telexy/Fusion/FusionDS.py
Telexy/Fusion/REST.py
Telexy/Fusion/__init__.py
Telexy/Jupyter/FusionContentManager.py
Telexy/Jupyter/__init__.py
telexy-1.23.816.dist-info/LICENSE.txt
telexy-1.23.816.dist-info/METADATA
telexy-1.23.816.dist-info/WHEEL
telexy-1.23.816.dist-info/top_level.txt
telexy-1.23.816.dist-info/RECORD
