Metadata-Version: 2.1
Name: telexy
Version: 1.23.816
Summary: Interface with Telexy Cloud
Author: Telexy
Author-email: support@telexy.com
Classifier: Programming Language :: Python :: 3
Classifier: License :: OSI Approved :: MIT License
Classifier: Operating System :: OS Independent
Requires-Python: >=3.10
License-File: LICENSE.txt
Requires-Dist: requests
Requires-Dist: jupyter
